certbot_dns_netcup.py
certbot_dns_netcup-2.0.0.dist-info/licenses/LICENSE.txt
certbot_dns_netcup-2.0.0.dist-info/METADATA
certbot_dns_netcup-2.0.0.dist-info/WHEEL
certbot_dns_netcup-2.0.0.dist-info/entry_points.txt
certbot_dns_netcup-2.0.0.dist-info/top_level.txt
certbot_dns_netcup-2.0.0.dist-info/RECORD
