Metadata-Version: 2.4
Name: certbot-dns-netcup
Version: 2.0.0
Summary: netcup DNS Authenticator plugin for Certbot
Home-page: https://github.com/coldfix/certbot-dns-netcup
Author: Thomas Gläßle
Author-email: thomas@coldfix.de
License: Apache License 2.0
Classifier: Development Status :: 5 - Production/Stable
Classifier: Environment :: Plugins
Classifier: Intended Audience :: System Administrators
Classifier: License :: OSI Approved :: Apache Software License
Classifier: Operating System :: POSIX :: Linux
Classifier: Programming Language :: Python :: 3
Classifier: Topic :: Internet :: WWW/HTTP
Classifier: Topic :: Security
Classifier: Topic :: System :: Installation/Setup
Classifier: Topic :: System :: Networking
Classifier: Topic :: System :: Systems Administration
Classifier: Topic :: Utilities
Requires-Python: >=3.7
License-File: LICENSE.txt
Requires-Dist: certbot>=2.7
Requires-Dist: requests
Dynamic: home-page
Dynamic: license-file
